CHANGES.md
CHANGES.txt
LICENSE.txt
MANIFEST.in
README.md
README.txt
launchkey.py
setup.py
launchkey_python.egg-info/PKG-INFO
launchkey_python.egg-info/SOURCES.txt
launchkey_python.egg-info/dependency_links.txt
launchkey_python.egg-info/not-zip-safe
launchkey_python.egg-info/requires.txt
launchkey_python.egg-info/top_level.txt