Metadata-Version: 1.1
Name: launchkey-python
Version: 1.3.0
Summary: LaunchKey Python SDK
Home-page: https://launchkey.com
Author: LaunchKey
Author-email: support@launchkey.com
License: MIT
Keywords: launchkey security authentication
Platform: UNKNOWN
Classifier: Programming Language :: Python
Classifier: Topic :: Internet :: WWW/HTTP
Classifier: Topic :: Internet :: WWW/HTTP :: WSGI :: Application
